Metadata-Version: 2.3
Name: swarmauri_middleware_ratepolicy
Version: 0.8.0.dev4
Summary: A middleware implementing rate policy and retry logic for Swarmauri
License: Apache-2.0
Keywords: swarmauri,middleware,ratepolicy,retry,tenacity,async,api,framework
Author: Jacob Stewart
Author-email: jacob@swarmauri.com
Requires-Python: >=3.10,<3.13
Classifier: License :: OSI Approved :: Apache Software License
Classifier: Natural Language :: English
Classifier: Programming Language :: Python :: 3.10
Classifier: Programming Language :: Python :: 3.11
Classifier: Programming Language :: Python :: 3.12
Classifier: Programming Language :: Python :: 3.13
Classifier: Development Status :: 3 - Alpha
Classifier: Intended Audience :: Developers
Classifier: Topic :: Software Development :: Libraries :: Application Frameworks
Requires-Dist: swarmauri_base
Requires-Dist: swarmauri_core
Requires-Dist: swarmauri_standard
Requires-Dist: tenacity
